docassemblecli/__init__.py
docassemblecli/commands.py
docassemblecli-0.0.23.dist-info/licenses/LICENSE.txt
docassemblecli-0.0.23.dist-info/METADATA
docassemblecli-0.0.23.dist-info/WHEEL
docassemblecli-0.0.23.dist-info/entry_points.txt
docassemblecli-0.0.23.dist-info/top_level.txt
docassemblecli-0.0.23.dist-info/RECORD
