Metadata-Version: 2.4
Name: docassemblecli
Version: 0.0.23
Summary: CLI utilities for using docassemble
Author-email: Jonathan Pyle <jhpyle@gmail.com>
Project-URL: Homepage, https://github.com/jhpyle/docassemblecli
Project-URL: Bug Tracker, https://github.com/jhpyle/docassemblecli/issues
Classifier: License :: OSI Approved :: MIT License
Classifier: Operating System :: OS Independent
Requires-Python: >=3.8
License-File: LICENSE.txt
Requires-Dist: pyyaml
Requires-Dist: requests
Requires-Dist: packaging
Requires-Dist: watchdog
Dynamic: license-file
